README.rst
noophttp.py
setup.py
noophttp.egg-info/PKG-INFO
noophttp.egg-info/SOURCES.txt
noophttp.egg-info/dependency_links.txt
noophttp.egg-info/entry_points.txt
noophttp.egg-info/requires.txt
noophttp.egg-info/top_level.txt