Metadata-Version: 1.0
Name: noophttp
Version: 1.0
Summary: Serve an empty response on HTTP, for example to block adds
Home-page: https://github.com/grimborg/noophttp
Author: Òscar Vilaplana
Author-email: dev@oscarvilaplana.cat
License: http://www.gnu.org/licenses/gpl-2.0.html
Platform: UNKNOWN
